eitaa/__init__.py
eitaa-2.3.1.dist-info/licenses/LICENSE
eitaa-2.3.1.dist-info/METADATA
eitaa-2.3.1.dist-info/WHEEL
eitaa-2.3.1.dist-info/top_level.txt
eitaa-2.3.1.dist-info/RECORD
