Metadata-Version: 2.4
Name: eitaa
Version: 2.3.1
Home-page: https://github.com/bistcuite/eitaapykit
License-File: LICENSE
Requires-Dist: requests
Requires-Dist: bs4
Dynamic: description
Dynamic: description-content-type
Dynamic: home-page
Dynamic: license-file
Dynamic: requires-dist
